[
  {
    "topic": "Classification of Elements and Periodicity in Properties 08 : Summary + PYQs (No DPP)",
    "url": "e90e1062-d12a-4570-b105-f01e10e831eb",
    "date": "",
    "duration": "01:45:46",
    "image": "https://d2bps9p1kiy4ka.cloudfront.net/5eb393ee95fab7468a79d189/53c9c13e-58f6-44a9-8238-adfba518a9e6.png",
    "n_name": "Classification of Elements and Periodicity in Properties 08 : Classnotes",
    "n_pdf": "9d1fc031-8bee-43c9-aba8-e328ec43b530",
    "d_name": "",
    "d_pdf": "",
    "q_name": "",
    "dq": "",
    "question": "40 Marks | 0 Mins | 10 Questions"
  },
  {
    "topic": "Classification of Elements and Periodicity in Properties 07 : Periodic Trends- Electronegativity",
    "url": "36038fb8-ce4a-4e07-8cad-4ada235fb469",
    "date": "",
    "duration": "01:36:19",
    "image": "https://d2bps9p1kiy4ka.cloudfront.net/5eb393ee95fab7468a79d189/f3b4019c-4901-48d0-8fd8-4ec97155d465.png",
    "n_name": "Classification of Elements and Periodicity in Properties 07 : Classnotes",
    "n_pdf": "9a6cafcb-fd6d-48aa-8951-012204fae249",
    "d_name": "",
    "d_pdf": "",
    "q_name": "",
    "dq": "",
    "question": "40 Marks | 0 Mins | 10 Questions"
  },
  {
    "topic": "Classification of Elements and Periodicity in Properties 06 : Periodic Trends- Electron Gain Enthalpy",
    "url": "f0eb21e0-9ee1-481e-a77d-ccb393536b48",
    "date": "",
    "duration": "01:36:52",
    "image": "https://d2bps9p1kiy4ka.cloudfront.net/5eb393ee95fab7468a79d189/93364fd2-d195-456d-b5d6-36c9751630ea.png",
    "n_name": "Classification of Elements and Periodicity in Properties 06 : Classnotes",
    "n_pdf": "f9232ffe-ae26-4b69-a331-de47c5806990",
    "d_name": "",
    "d_pdf": "",
    "q_name": "",
    "dq": "",
    "question": "40 Marks | 0 Mins | 10 Questions"
  },
  {
    "topic": "Classification of Elements and Periodicity in Properties 05 : Periodic Trends- Ionic Radius || Ionisation Energy",
    "url": "f7e1f1c0-22ae-4a47-9549-f4a9615fa067",
    "date": "",
    "duration": "01:51:28",
    "image": "https://d2bps9p1kiy4ka.cloudfront.net/5eb393ee95fab7468a79d189/187d0d44-ec16-49b5-8fb5-0096ea547ed3.png",
    "n_name": "Classification of Elements and Periodicity in Properties 05 : Classnotes",
    "n_pdf": "2768598a-135b-4242-9cae-75a069a1b1a3",
    "d_name": "",
    "d_pdf": "",
    "q_name": "",
    "dq": "",
    "question": "40 Marks | 0 Mins | 10 Questions"
  },
  {
    "topic": "Classification of Elements and Periodicity in Properties : Slater’s Rule || Extra Lecture (No DPP)",
    "url": "f8bace7c-4438-43b1-89c7-da2e271cfa24",
    "date": "",
    "duration": "01:09:46",
    "image": "https://d2bps9p1kiy4ka.cloudfront.net/5eb393ee95fab7468a79d189/f957795a-6f80-4c5a-8bbc-72cc498dd0ff.png",
    "n_name": "Classification of Elements and Periodicity in Properties : Extra Lecture Classnotes",
    "n_pdf": "cf643d0b-de4d-4e41-8e7d-70fe42d7ab99",
    "d_name": "",
    "d_pdf": "",
    "q_name": "",
    "dq": "",
    "question": "40 Marks | 0 Mins | 10 Questions"
  },
  {
    "topic": "Classification of Elements and Periodicity in Properties 04 : Periodic Trends-Atomic Size",
    "url": "fea8ff9e-5187-47d7-bc4c-5ab4707525c7",
    "date": "",
    "duration": "01:49:04",
    "image": "https://d2bps9p1kiy4ka.cloudfront.net/5eb393ee95fab7468a79d189/a8b9d099-8ffe-4b29-a02f-c2371ede308b.png",
    "n_name": "Classification of Elements and Periodicity in Properties 04 : Classnotes",
    "n_pdf": "e8bfd297-597b-4244-a942-9e3783366a89",
    "d_name": "",
    "d_pdf": "",
    "q_name": "",
    "dq": "",
    "question": "40 Marks | 0 Mins | 10 Questions"
  },
  {
    "topic": "Classification of Elements and Periodicity in Properties 03 : Block || Groups & Periods",
    "url": "af9000e9-c60c-4209-9264-cdb9902484b3",
    "date": "",
    "duration": "01:38:54",
    "image": "https://d2bps9p1kiy4ka.cloudfront.net/5eb393ee95fab7468a79d189/0e73728a-592e-412a-81ef-a0bd3dfad17e.png",
    "n_name": "Classification of Elements and Periodicity in Properties 03 : Classnotes",
    "n_pdf": "57fc71bd-5d62-4238-a1b3-7e128bfa6959",
    "d_name": "",
    "d_pdf": "",
    "q_name": "",
    "dq": "",
    "question": "40 Marks | 0 Mins | 10 Questions"
  },
  {
    "topic": "Classification of Elements and Periodicity in Properties 02 : Modern Periodic Table",
    "url": "829359f4-e7b0-4c6c-a8d6-4d838969571b",
    "date": "",
    "duration": "01:36:07",
    "image": "https://d2bps9p1kiy4ka.cloudfront.net/5eb393ee95fab7468a79d189/b4220ade-0846-4c34-af9c-a2588d2f08eb.png",
    "n_name": "Classification of Elements and Periodicity in Properties 02 : Classnotes",
    "n_pdf": "82d6156e-0e1e-4201-ba61-617fc3697dc4",
    "d_name": "",
    "d_pdf": "",
    "q_name": "",
    "dq": "",
    "question": "40 Marks | 0 Mins | 10 Questions"
  },
  {
    "topic": "Classification of Elements and Periodicity in Properties 01 : Genesis of Periodic Classification",
    "url": "691d7b11-0056-4fde-82b1-2ed0ce49b516",
    "date": "",
    "duration": "01:38:34",
    "image": "https://d2bps9p1kiy4ka.cloudfront.net/5eb393ee95fab7468a79d189/471511bc-2be3-4f68-b3df-fe11dde4a935.png",
    "n_name": "Classification of Elements and Periodicity in Properties 01 : Classnotes",
    "n_pdf": "c739feec-da40-4abd-89d0-9240c16e64d7",
    "d_name": "",
    "d_pdf": "",
    "q_name": "",
    "dq": "",
    "question": "40 Marks | 0 Mins | 10 Questions"
  }
]
